{"format":2,"version":"5.3","globals":"45fb87dcd1251109c254273a76c6d399","files":{"Calendar_py":{"hash":"adea76b1c6b5c8fbba07c15944bbd7fd","index":{"nums":[1,353,0,21,144,7,13],"html_filename":"Calendar_py.html","relative_filename":"Calendar.py"}},"CalendarTest_py":{"hash":"8d4b54a02fc12b13111bee7c30825c2b","index":{"nums":[1,422,0,0,2,0,0],"html_filename":"CalendarTest_py.html","relative_filename":"CalendarTest.py"}},"CalendarTestRunCalendar_py":{"hash":"8b35b483ec782fac33e2230c12d9d49a","index":{"nums":[1,120,0,0,0,0,0],"html_filename":"CalendarTestRunCalendar_py.html","relative_filename":"CalendarTestRunCalendar.py"}}}}